mondrian/__init__.py
mondrian/_version.py
mondrian/errors.py
mondrian/filters.py
mondrian/formatters.py
mondrian/humanizer.py
mondrian/levels.py
mondrian/settings.py
mondrian/styles.py
mondrian/term.py
mondrian/contrib/__init__.py
mondrian/contrib/stackdriver.py
mondrian-0.8.1.dist-info/METADATA
mondrian-0.8.1.dist-info/WHEEL
mondrian-0.8.1.dist-info/top_level.txt
mondrian-0.8.1.dist-info/RECORD
