Metadata-Version: 2.1
Name: mondrian
Version: 0.8.1
Summary: Mondrian helps you to configure and use python's logging module once and for ever.
Home-page: https://python-mondrian.github.io/
Author: Romain Dorgueil
Author-email: romain@dorgueil.net
License: Apache License, Version 2.0
Download-URL: https://github.com/python-mondrian/mondrian/archive/0.8.1.tar.gz
Platform: UNKNOWN
Provides-Extra: dev
